redzone/__init__.py
redzone/bootstrap.py
redzone/context.py
redzone/auth/__init__.py
redzone/auth/auth.py
redzone/caches/__init__.py
redzone/caches/cache.py
redzone/caches/service_token_cache.py
redzone/event_buses/__init__.py
redzone/event_buses/event_bus.py
redzone/exceptions/__init__.py
redzone/exceptions/auth_exceptions.py
redzone/handlers/__init__.py
redzone/handlers/api_creator.py
redzone/handlers/decorators.py
redzone/handlers/events_listener_creator.py
redzone/handlers/local_events_listener.py
redzone/handlers/events/__init__.py
redzone/handlers/events/abstract_event_handler.py
redzone/handlers/events/event.py
redzone/handlers/events/event_handler_factory.py
redzone/middleware/__init__.py
redzone/middleware/database_session_middleware.py
redzone/middleware/internal_server_error_middleware.py
redzone/middleware/logging_middleware.py
redzone/middleware/trace_middleware.py
redzone/objects/__init__.py
redzone/objects/base_object.py
redzone/objects/service_token.py
redzone/schemas/__init__.py
redzone/schemas/base_schemas.py
redzone/schemas/index_schemas.py
redzone/services/__init__.py
redzone/services/auth_service.py
redzone/services/service.py
redzone/settings/__init__.py
redzone/utils/__init__.py
redzone/utils/database.py
redzone/utils/logger.py
redzone/utils/trace.py
redzone/utils/workflow_tracker.py
redzone_lib-1.0.10.dist-info/METADATA
redzone_lib-1.0.10.dist-info/WHEEL
redzone_lib-1.0.10.dist-info/top_level.txt
redzone_lib-1.0.10.dist-info/RECORD
