Metadata-Version: 2.4
Name: redzone-lib
Version: 1.0.10
Summary: Contains common utilities for use across Redzone projects
Author: RedZone Co
Author-email: info@redzone.co
License: MIT
Requires-Python: >=3.10
Dynamic: author
Dynamic: author-email
Dynamic: description
Dynamic: description-content-type
Dynamic: license
Dynamic: requires-python
Dynamic: summary
